docwriter/__init__.py
docwriter/__main__.py
docwriter/check.py
docwriter/content.py
docwriter/formatter.py
docwriter/siteconfig.py
docwriter/sources.py
docwriter/tomarkdown.py
docwriter/utils.py
docwriter-1.3.3.dist-info/METADATA
docwriter-1.3.3.dist-info/WHEEL
docwriter-1.3.3.dist-info/top_level.txt
docwriter-1.3.3.dist-info/RECORD
