Metadata-Version: 2.1
Name: docwriter
Version: 1.3.3
Summary: API reference documentation generator for FreeType.
Home-page: https://gitlab.freedesktop.org/freetype/docwriter
Author: Nikhil Ramakrishnan
Author-email: freetype-devel@nongnu.org
License: FreeType License
Keywords: freetype docwriter
Platform: UNKNOWN
Classifier: Development Status :: 5 - Production/Stable
Classifier: Environment :: Console
Classifier: Intended Audience :: Developers
Classifier: Operating System :: OS Independent
Classifier: Programming Language :: Python
Classifier: Topic :: Documentation
Classifier: Topic :: Text Processing
Requires-Python: >=3.5
Requires-Dist: mistune <3.0,>=0.8.4
Requires-Dist: mkdocs >=1.4.3
Requires-Dist: mkdocs-material >=8.2.6
Requires-Dist: PyYAML >=5.4.1
